README.md
setup.py
xem/__init__.py
xem/__main__.py
xem/gapp.py
xem/models.py
xem/server.py
xem/stats.py
xem.egg-info/PKG-INFO
xem.egg-info/SOURCES.txt
xem.egg-info/dependency_links.txt
xem.egg-info/not-zip-safe
xem.egg-info/requires.txt
xem.egg-info/top_level.txt
xem/templates/index.html
xem/templates/test.html