Metadata-Version: 2.1
Name: xem
Version: 0.0.6
Summary: A lightweight self-hosted web analytics server written in Flask and python.
Home-page: https://github.com/huyng/xem
Author: Huy Nguyen
Author-email: 121183+huyng@users.noreply.github.com
License: UNKNOWN
Platform: UNKNOWN
